[{"id":"kpop_nct-riize-","name":"あじくらや テヨン・マーク・ショウタロウ（RIIZE）","genre":"others","prefecture":"大阪府","city":"大阪市","lat":34.666303,"lng":135.5220024,"youtube_id":"","source_video_title":"NCT","visited_date":"","members":[],"groups":["kpop_nct"],"group":"kpop_nct","nearest_station":"大阪上本町駅 徒歩3分","tags":[],"thumbnail_url":"","source_type":""},{"id":"kpop_nct-8be1f22b-","name":"サーティーワン上本町店","genre":"others","prefecture":"大阪府","city":"大阪市","lat":34.666526,"lng":135.5217554,"youtube_id":"","source_video_title":"NCT","visited_date":"","members":[],"groups":["kpop_nct"],"group":"kpop_nct","nearest_station":"大阪上本町駅 徒歩3分","tags":[],"thumbnail_url":"","source_type":""},{"id":"kpop_nct-nct_2018-","name":"ヒルトン大阪（NCT 2018）","genre":"others","prefecture":"大阪府","city":"大阪市","lat":34.7001688,"lng":135.4979709,"youtube_id":"","source_video_title":"NCT","visited_date":"","members":[],"groups":["kpop_nct"],"group":"kpop_nct","nearest_station":"大阪梅田駅 徒歩3分","tags":[],"thumbnail_url":"","source_type":""},{"id":"kpop_nct-3cab94de-","name":"道頓堀 テヨン","genre":"others","prefecture":"大阪府","city":"大阪市","lat":34.64504076430828,"lng":135.51379439372175,"youtube_id":"","source_video_title":"NCT","visited_date":"","members":[],"groups":["kpop_nct"],"group":"kpop_nct","nearest_station":"","tags":[],"thumbnail_url":"https://tblg.k-img.com/resize/640x640c/restaurant/images/Rvw/208953/676239666bd6ad68c726e387a6f575e5.jpg?token=cf4bb39&api=v2","source_type":"","tabelog_score":3.43,"price_range":"￥1,000～￥1,999"}]