[
  {
    "id": "kanjani-ツナグ茶房",
    "name": "ツナグ茶房",
    "group": "kanjani",
    "groups": [
      "kanjani"
    ],
    "genre": "カフェ",
    "prefecture": "大阪府",
    "members": [
      "大倉忠義"
    ],
    "source_url": "https://ameblo.jp/yocorino-caputino/entry-12960510668.html",
    "source_video_title": "関ジャニ∞ロケ地巡り - ツナグ茶房〜俊徳道･布施ぶらり①〜",
    "description": "",
    "source_type": "blog",
    "city": "東大阪市"
  },
  {
    "id": "kanjani-鉄板呑み屋ブッチャー",
    "name": "鉄板呑み屋ブッチャー",
    "group": "kanjani",
    "groups": [
      "kanjani"
    ],
    "genre": "居酒屋",
    "prefecture": "大阪府",
    "members": [
      "渋谷すばる"
    ],
    "source_url": "https://ameblo.jp/yocorino-caputino/entry-12560728048.html",
    "source_video_title": "関ジャニ∞ロケ地巡り - 鉄板呑み屋ブッチャー@堀江∞",
    "description": "",
    "source_type": "blog",
    "city": "大阪市"
  },
  {
    "id": "kanjani-はちまき",
    "name": "はちまき",
    "group": "kanjani",
    "groups": [
      "kanjani"
    ],
    "genre": "食事",
    "prefecture": "東京都",
    "members": [
      "錦戸亮"
    ],
    "source_url": "https://ameblo.jp/yocorino-caputino/entry-12525585549.html",
    "source_video_title": "関ジャニ∞ロケ地巡り - はちまき∞神保町ロケ地〜9/3東京⑦〜",
    "description": "",
    "source_type": "blog",
    "city": "千代田区"
  },
  {
    "id": "kanjani-ひみつ堂",
    "name": "ひみつ堂",
    "group": "kanjani",
    "groups": [
      "kanjani"
    ],
    "genre": "スイーツ",
    "prefecture": "東京都",
    "members": [],
    "source_url": "https://ameblo.jp/yocorino-caputino/entry-12524064320.html",
    "source_video_title": "関ジャニ∞ロケ地巡り - ひみつ堂∞〜9/1東京①〜",
    "description": "",
    "source_type": "blog",
    "city": "台東区"
  },
  {
    "id": "kanjani-shinshin-住吉店",
    "name": "ShinShin 住吉店",
    "group": "kanjani",
    "groups": [
      "kanjani"
    ],
    "genre": "ラーメン",
    "prefecture": "福岡県",
    "members": [
      "渋谷すばる",
      "錦戸亮"
    ],
    "source_url": "https://ameblo.jp/yocorino-caputino/entry-12503807640.html",
    "source_video_title": "関ジャニ∞ロケ地巡り - ShinShin@住吉店∞〜8/2福岡⑤〜",
    "description": "",
    "source_type": "blog",
    "city": "福岡市"
  },
  {
    "id": "kanjani-若駒",
    "name": "若駒",
    "group": "kanjani",
    "groups": [
      "kanjani"
    ],
    "genre": "食事",
    "prefecture": "北海道",
    "members": [
      "横山裕",
      "錦戸亮"
    ],
    "source_url": "https://ameblo.jp/yocorino-caputino/entry-12494981250.html",
    "source_video_title": "関ジャニ∞ロケ地巡り - 若駒∞～札幌⑤★3日目～",
    "description": "",
    "source_type": "blog",
    "city": "札幌市"
  },
  {
    "id": "kanjani-コロンボ",
    "name": "コロンボ",
    "group": "kanjani",
    "groups": [
      "kanjani"
    ],
    "genre": "カフェ",
    "prefecture": "大阪府",
    "members": [],
    "source_url": "https://ameblo.jp/yocorino-caputino/entry-12484971783.html",
    "source_video_title": "関ジャニ∞ロケ地巡り - コロンボ.関テレ〜大阪∞②〜",
    "description": "",
    "source_type": "blog",
    "city": "大阪市"
  },
  {
    "id": "kanjani-ちばチャン",
    "name": "ちばチャン",
    "group": "kanjani",
    "groups": [
      "kanjani"
    ],
    "genre": "ラーメン",
    "prefecture": "東京都",
    "members": [
      "錦戸亮"
    ],
    "source_url": "https://ameblo.jp/yocorino-caputino/entry-12481273784.html",
    "source_video_title": "関ジャニ∞ロケ地巡り - ちばチャン@錦糸町〜6/5東京∞ロケ地③〜",
    "description": "",
    "source_type": "blog",
    "city": "墨田区"
  },
  {
    "id": "kanjani-ラドリオ",
    "name": "ラドリオ",
    "group": "kanjani",
    "groups": [
      "kanjani"
    ],
    "genre": "カフェ",
    "prefecture": "東京都",
    "members": [
      "丸山隆平",
      "錦戸亮"
    ],
    "source_url": "https://ameblo.jp/yocorino-caputino/entry-12473329011.html",
    "source_video_title": "関ジャニ∞ロケ地巡り - ラドリオ@神保町〜6/5東京∞ロケ地①〜",
    "description": "",
    "source_type": "blog",
    "city": "千代田区"
  }
]